rttt/__init__.py
rttt/__main__.py
rttt/cli.py
rttt/connectors/__init__.py
rttt/connectors/base.py
rttt/connectors/demo.py
rttt/connectors/file_log.py
rttt/connectors/pylink_rtt.py
rttt/console.py
rttt/event.py
rttt/lexer.py
rttt/ui.py
rttt-1.3.3.dist-info/LICENSE
rttt-1.3.3.dist-info/METADATA
rttt-1.3.3.dist-info/WHEEL
rttt-1.3.3.dist-info/entry_points.txt
rttt-1.3.3.dist-info/RECORD
